sparkdantic/__init__.py
sparkdantic/exceptions.py
sparkdantic/model.py
sparkdantic/py.typed
sparkdantic/utils.py
sparkdantic-2.7.0.dist-info/METADATA
sparkdantic-2.7.0.dist-info/WHEEL
sparkdantic-2.7.0.dist-info/licenses/LICENSE
sparkdantic-2.7.0.dist-info/RECORD
