Metadata-Version: 2.4
Name: sparkdantic
Version: 2.7.0
Summary: A pydantic -> spark schema library
License-File: LICENSE
Author: Mitchell Lisle
Author-email: m.lisle90@gmail.com
Requires-Python: >3.9.1,<4.0.0
Classifier: Programming Language :: Python :: 3
Classifier: Programming Language :: Python :: 3.10
Classifier: Programming Language :: Python :: 3.11
Classifier: Programming Language :: Python :: 3.12
Classifier: Programming Language :: Python :: 3.13
Classifier: Programming Language :: Python :: 3.14
Provides-Extra: pyspark
Requires-Dist: jinja2 (>=3.1.6)
Requires-Dist: jmespath (>=1.0.1,<2.0.0)
Requires-Dist: packaging (>=24.2,<26.0)
Requires-Dist: pydantic (>=2.1.1,<3.0.0)
Requires-Dist: pyparsing (>=3.1.1,<4.0.0)
Requires-Dist: pyspark (>=3.3.0,<=4.0.1) ; extra == "pyspark"
